[
  {
    "slug": "residential-interior-design-bur-dubai",
    "serviceName": "Residential Interior Design bur-dubai"
  },
  {
    "slug": "office-interior-design-bur-dubai",
    "serviceName": "Office Interior Design bur-dubai"
  },
  {
    "slug": "commercial-interior-design-bur-dubai",
    "serviceName": "Commercial Interior Design bur-dubai"
  },
  {
    "slug": "villa-interior-design-bur-dubai",
    "serviceName": "Villa Interior Design bur-dubai"
  },
  {
    "slug": "apartment-interior-design-bur-dubai",
    "serviceName": "Apartment Interior Design bur-dubai"
  },
  {
    "slug": "penthouse-interior-design-bur-dubai",
    "serviceName": "Penthouse Interior Design bur-dubai"
  },
  {
    "slug": "luxury-interior-design-bur-dubai",
    "serviceName": "Luxury Interior Design bur-dubai"
  },
  {
    "slug": "modern-interior-design-bur-dubai",
    "serviceName": "Modern Interior Design bur-dubai"
  },
  {
    "slug": "minimalist-interior-design-bur-dubai",
    "serviceName": "Minimalist Interior Design bur-dubai"
  },
  {
    "slug": "contemporary-interior-design-bur-dubai",
    "serviceName": "Contemporary Interior Design bur-dubai"
  },
  {
    "slug": "arabic-style-interior-design-bur-dubai",
    "serviceName": "Arabic Style Interior Design bur-dubai"
  },
  {
    "slug": "kitchen-interior-design-bur-dubai",
    "serviceName": "Kitchen Interior Design bur-dubai"
  },
  {
    "slug": "modular-kitchens-bur-dubai",
    "serviceName": "Modular Kitchens bur-dubai"
  },
  {
    "slug": "wardrobe-design-bur-dubai",
    "serviceName": "Wardrobe Design bur-dubai"
  },
  {
    "slug": "closet-design-bur-dubai",
    "serviceName": "Closet Design bur-dubai"
  },
  {
    "slug": "bathroom-interior-design-bur-dubai",
    "serviceName": "Bathroom Interior Design bur-dubai"
  },
  {
    "slug": "living-room-interior-design-bur-dubai",
    "serviceName": "Living Room Interior Design bur-dubai"
  },
  {
    "slug": "bedroom-interior-design-bur-dubai",
    "serviceName": "Bedroom Interior Design bur-dubai"
  },
  {
    "slug": "dining-room-interior-design-bur-dubai",
    "serviceName": "Dining Room Interior Design bur-dubai"
  },
  {
    "slug": "home-office-interior-design-bur-dubai",
    "serviceName": "Home Office Interior Design bur-dubai"
  },
  {
    "slug": "office-fit-out-bur-dubai",
    "serviceName": "Office Fit Out bur-dubai"
  },
  {
    "slug": "corporate-office-interior-design-bur-dubai",
    "serviceName": "Corporate Office Interior Design bur-dubai"
  },
  {
    "slug": "retail-shop-interior-design-bur-dubai",
    "serviceName": "Retail Shop Interior Design bur-dubai"
  },
  {
    "slug": "mall-interior-design-bur-dubai",
    "serviceName": "Mall Interior Design bur-dubai"
  },
  {
    "slug": "restaurant-interior-design-bur-dubai",
    "serviceName": "Restaurant Interior Design bur-dubai"
  },
  {
    "slug": "cafe-interior-design-bur-dubai",
    "serviceName": "Cafe Interior Design bur-dubai"
  },
  {
    "slug": "hotel-interior-design-bur-dubai",
    "serviceName": "Hotel Interior Design bur-dubai"
  },
  {
    "slug": "showroom-interior-design-bur-dubai",
    "serviceName": "Showroom Interior Design bur-dubai"
  },
  {
    "slug": "clinic-interior-design-bur-dubai",
    "serviceName": "Clinic Interior Design bur-dubai"
  },
  {
    "slug": "healthcare-interior-design-bur-dubai",
    "serviceName": "Healthcare Interior Design bur-dubai"
  },
  {
    "slug": "salon-interior-design-bur-dubai",
    "serviceName": "Salon Interior Design bur-dubai"
  },
  {
    "slug": "spa-interior-design-bur-dubai",
    "serviceName": "Spa Interior Design bur-dubai"
  },
  {
    "slug": "custom-furniture-design-bur-dubai",
    "serviceName": "Custom Furniture Design bur-dubai"
  },
  {
    "slug": "bespoke-furniture-design-bur-dubai",
    "serviceName": "Bespoke Furniture Design bur-dubai"
  },
  {
    "slug": "lighting-design-bur-dubai",
    "serviceName": "Lighting Design bur-dubai"
  },
  {
    "slug": "lighting-automation-bur-dubai",
    "serviceName": "Lighting Automation bur-dubai"
  },
  {
    "slug": "smart-lighting-bur-dubai",
    "serviceName": "Smart Lighting bur-dubai"
  },
  {
    "slug": "wall-flooring-design-bur-dubai",
    "serviceName": "Wall & Flooring Design bur-dubai"
  },
  {
    "slug": "wallpaper-design-bur-dubai",
    "serviceName": "Wallpaper Design bur-dubai"
  },
  {
    "slug": "wall-coverings-bur-dubai",
    "serviceName": "Wall Coverings bur-dubai"
  },
  {
    "slug": "window-blinds-bur-dubai",
    "serviceName": "Window Blinds bur-dubai"
  },
  {
    "slug": "window-curtains-bur-dubai",
    "serviceName": "Window Curtains bur-dubai"
  },
  {
    "slug": "drapes-bur-dubai",
    "serviceName": "Drapes bur-dubai"
  },
  {
    "slug": "home-decor-consultation-bur-dubai",
    "serviceName": "Home Decor Consultation bur-dubai"
  },
  {
    "slug": "color-theme-consultation-bur-dubai",
    "serviceName": "Color Theme Consultation bur-dubai"
  },
  {
    "slug": "art-consultation-bur-dubai",
    "serviceName": "Art Consultation bur-dubai"
  },
  {
    "slug": "home-remodeling-bur-dubai",
    "serviceName": "Home Remodeling bur-dubai"
  },
  {
    "slug": "home-renovation-bur-dubai",
    "serviceName": "Home Renovation bur-dubai"
  },
  {
    "slug": "office-renovation-bur-dubai",
    "serviceName": "Office Renovation bur-dubai"
  },
  {
    "slug": "space-planning-bur-dubai",
    "serviceName": "Space Planning bur-dubai"
  },
  {
    "slug": "interior-space-optimization-bur-dubai",
    "serviceName": "Interior Space Optimization bur-dubai"
  },
  {
    "slug": "3d-interior-rendering-bur-dubai",
    "serviceName": "3D Interior Rendering bur-dubai"
  },
  {
    "slug": "interior-visualization-bur-dubai",
    "serviceName": "Interior Visualization bur-dubai"
  },
  {
    "slug": "sustainable-interior-design-bur-dubai",
    "serviceName": "Sustainable Interior Design bur-dubai"
  },
  {
    "slug": "eco-friendly-interior-design-bur-dubai",
    "serviceName": "Eco-Friendly Interior Design bur-dubai"
  },
  {
    "slug": "smart-home-interior-design-bur-dubai",
    "serviceName": "Smart Home Interior Design bur-dubai"
  },
  {
    "slug": "acoustic-design-bur-dubai",
    "serviceName": "Acoustic Design bur-dubai"
  },
  {
    "slug": "soundproofing-design-bur-dubai",
    "serviceName": "Soundproofing Design bur-dubai"
  },
  {
    "slug": "balcony-interior-design-bur-dubai",
    "serviceName": "Balcony Interior Design bur-dubai"
  },
  {
    "slug": "terrace-interior-design-bur-dubai",
    "serviceName": "Terrace Interior Design bur-dubai"
  },
  {
    "slug": "outdoor-living-design-bur-dubai",
    "serviceName": "Outdoor Living Design bur-dubai"
  },
  {
    "slug": "media-room-interior-design-bur-dubai",
    "serviceName": "Media Room Interior Design bur-dubai"
  },
  {
    "slug": "home-theater-interior-design-bur-dubai",
    "serviceName": "Home Theater Interior Design bur-dubai"
  },
  {
    "slug": "kids-interior-design-bur-dubai",
    "serviceName": "Kids Interior Design bur-dubai"
  },
  {
    "slug": "childrens-room-interior-design-bur-dubai",
    "serviceName": "Children's Room Interior Design bur-dubai"
  },
  {
    "slug": "co-working-space-interior-design-bur-dubai",
    "serviceName": "Co-Working Space Interior Design bur-dubai"
  },
  {
    "slug": "gym-interior-design-bur-dubai",
    "serviceName": "Gym Interior Design bur-dubai"
  },
  {
    "slug": "fitness-studio-interior-design-bur-dubai",
    "serviceName": "Fitness Studio Interior Design bur-dubai"
  },
  {
    "slug": "event-hall-interior-design-bur-dubai",
    "serviceName": "Event Hall Interior Design bur-dubai"
  },
  {
    "slug": "banquet-hall-interior-design-bur-dubai",
    "serviceName": "Banquet Hall Interior Design bur-dubai"
  },
  {
    "slug": "budget-interior-solutions-bur-dubai",
    "serviceName": "Budget Interior Solutions bur-dubai"
  },
  {
    "slug": "affordable-interior-solutions-bur-dubai",
    "serviceName": "Affordable Interior Solutions bur-dubai"
  },
  {
    "slug": "interior-design-bur-dubai",
    "serviceName": "Interior Design bur-dubai"
  }
]